UserGuide/__init__.py
MESSI_RCCLab-0.0.12.dist-info/LICENCE
MESSI_RCCLab-0.0.12.dist-info/METADATA
MESSI_RCCLab-0.0.12.dist-info/WHEEL
MESSI_RCCLab-0.0.12.dist-info/entry_points.txt
MESSI_RCCLab-0.0.12.dist-info/top_level.txt
MESSI_RCCLab-0.0.12.dist-info/RECORD
