Metadata-Version: 2.1
Name: MESSI-RCCLab
Version: 0.0.12
Summary: MESSI: Multi Ensamble Strategy for Structural Elucidation
Author: María M. Zanardi & Ariel M. Sarotti
Author-email: zanardi@inv.rosario-conicet.gov.ar
License: MIT
Keywords: NMR structural elucidation
Classifier: Programming Language :: Python :: 3
Classifier: License :: OSI Approved :: MIT License
Classifier: Operating System :: OS Independent
License-File: LICENCE
Requires-Dist: tk
Requires-Dist: pandas
Requires-Dist: numpy
Requires-Dist: sklearn
Requires-Dist: scipy
Requires-Dist: openpyxl
Requires-Dist: pathlib
Requires-Dist: scikit-learn
